phub/__init__.py
phub/__main__.py
phub/consts.py
phub/core.py
phub/errors.py
phub/literals.py
phub/utils.py
phub/modules/__init__.py
phub/modules/display.py
phub/modules/parser.py
phub/modules/rss.py
phub/objects/__init__.py
phub/objects/account.py
phub/objects/data.py
phub/objects/feed.py
phub/objects/image.py
phub/objects/playlist.py
phub/objects/query.py
phub/objects/user.py
phub/objects/video.py
phub/tests/__init__.py
phub/tests/test_auth.py
phub/tests/test_model.py
phub/tests/test_playlist.py
phub/tests/test_search.py
phub/tests/test_video.py
phub-4.8.7.dist-info/licenses/LICENSE
phub-4.8.7.dist-info/METADATA
phub-4.8.7.dist-info/WHEEL
phub-4.8.7.dist-info/entry_points.txt
phub-4.8.7.dist-info/top_level.txt
phub-4.8.7.dist-info/RECORD
