Metadata-Version: 2.4
Name: phub
Version: 4.8.7
Summary: An API for Pornhub
Author-email: Egsagon <egsagon.git@gmail.com>, EchterAlsFake <EchterAlsFake@proton.me>
License:                     GNU GENERAL PUBLIC LICENSE
Project-URL: Documentation, https://phub.readthedocs.io
Project-URL: Documentation_Updated, https://github.com/EchterAlsFake/API_Docs/blob/master/Porn_APIs/PHUB.md
Project-URL: Repository, https://github.com/EchterAlsFake/PHUB
Keywords: pornhub,phub,porn,api,web scrapper,api wrapper
Classifier: Development Status :: 4 - Beta
Classifier: Programming Language :: Python
Requires-Python: >=3.9
License-File: LICENSE
Requires-Dist: httpx[brotli,socks]
Requires-Dist: eaf_base_api
Requires-Dist: h2
Dynamic: license-file
